SCanalyzer/SCanalyzer.py
SCanalyzer/__init__.py
SCanalyzer/gtfs_edit.py
SCanalyzer/util.py
SCanalyzer/busSim/__init__.py
SCanalyzer/busSim/busSim.py
SCanalyzer/busSim/config.py
SCanalyzer/busSim/graph.py
SCanalyzer/busSim/manager/AWSManager.py
SCanalyzer/busSim/manager/__init__.py
SCanalyzer/busSim/manager/baseManager.py
SCanalyzer/busSim/manager/localManager.py
SCanalyzer/busSim/manager/managerFactory.py
SCanalyzer/census/Census.py
SCanalyzer/census/__init__.py
SCanalyzer/result/__init__.py
SCanalyzer/result/searchResult.py
SCanalyzer/service/__init__.py
SCanalyzer/service/yelp.py
SCanalyzer-0.0.2.dist-info/LICENSE
SCanalyzer-0.0.2.dist-info/METADATA
SCanalyzer-0.0.2.dist-info/WHEEL
SCanalyzer-0.0.2.dist-info/top_level.txt
SCanalyzer-0.0.2.dist-info/RECORD
