Metadata-Version: 2.1
Name: SCanalyzer
Version: 0.0.2
Summary: Service Cube Analyzer
Home-page: https://github.com/wisc-bus/simulator
Author: Chang Xu
Author-email: cxu249@wisc.edu
License: UNKNOWN
Platform: UNKNOWN
Classifier: Development Status :: 3 - Alpha
Classifier: License :: OSI Approved :: Apache Software License
Classifier: Operating System :: OS Independent
Classifier: Topic :: Scientific/Engineering :: GIS
Classifier: Programming Language :: Python :: 3
Requires-Python: >=3.6
Requires-Dist: requests
Requires-Dist: jupyter
Requires-Dist: matplotlib
Requires-Dist: pandas
Requires-Dist: geopandas
Requires-Dist: descartes
Requires-Dist: geopy
Requires-Dist: boto3
Requires-Dist: pyyaml
